aws_session_handler/__init__.py
aws_session_handler/awssessionhandler.py
aws_session_handler-0.0.3.dist-info/METADATA
aws_session_handler-0.0.3.dist-info/RECORD
aws_session_handler-0.0.3.dist-info/WHEEL
aws_session_handler-0.0.3.dist-info/top_level.txt
