Metadata-Version: 2.1
Name: aws-session-handler
Version: 0.0.3
Summary: AWS Session Handler
Home-page: https://github.com/MarioVerbelen/aws_session_handler
Author: MarioVerbelen
Author-email: mario@verbelen.org
License: MIT License
Download-URL: https://github.com/MarioVerbelen/aws_session_handler
Keywords: boto3 amazon web services aws authentication
Platform: UNKNOWN
